pip2p.py
pipp.py
pip2p-0.0.1.dist-info/METADATA
pip2p-0.0.1.dist-info/WHEEL
pip2p-0.0.1.dist-info/entry_points.txt
pip2p-0.0.1.dist-info/top_level.txt
pip2p-0.0.1.dist-info/RECORD
