Metadata-Version: 2.1
Name: pip2p
Version: 0.0.1
Summary: install private packages which store in svn repository
Home-page: UNKNOWN
Author: ticktick
Author-email: cyxia90s@163.com
License: MIT
Platform: UNKNOWN
Requires-Dist: Click
